varst/__init__.py
varst/application.py
varst/cli.py
varst/utils/__init__.py
varst/utils/parser.py
varst/utils/rst_file.py
varst/utils/substitution.py
varst-1.6.0.dist-info/entry_points.txt
varst-1.6.0.dist-info/METADATA
varst-1.6.0.dist-info/LICENSE
varst-1.6.0.dist-info/WHEEL
varst-1.6.0.dist-info/RECORD
