Metadata-Version: 2.1
Name: varst
Version: 1.6.0
Summary: Replace substitutions in rst files with variables.
Home-page: https://github.com/junghoon-vans/varst
License: MIT
Keywords: rst,reST,reStructuredText,replace,substitution
Author: junghoon-vans
Author-email: junghoon.ban@gmail.com
Maintainer: junghoon-vans
Maintainer-email: junghoon.ban@gmail.com
Requires-Python: >=3.9,<4.0
Classifier: Environment :: Console
Classifier: License :: OSI Approved :: MIT License
Classifier: Programming Language :: Python :: 3
Classifier: Programming Language :: Python :: 3.9
Classifier: Programming Language :: Python :: 3.10
Classifier: Programming Language :: Python :: 3.11
Classifier: Topic :: Documentation
Classifier: Topic :: Software Development :: Documentation
Classifier: Topic :: Text Processing
Project-URL: Documentation, https://varst.readthedocs.io/
Project-URL: Repository, https://github.com/junghoon-vans/varst
